Topsis_python/__init__.py
Topsis_python/__main__.py
Topsis_Divyansh_102003459-1.0.0.dist-info/LICENSE.txt
Topsis_Divyansh_102003459-1.0.0.dist-info/METADATA
Topsis_Divyansh_102003459-1.0.0.dist-info/WHEEL
Topsis_Divyansh_102003459-1.0.0.dist-info/entry_points.txt
Topsis_Divyansh_102003459-1.0.0.dist-info/top_level.txt
Topsis_Divyansh_102003459-1.0.0.dist-info/RECORD
